earlinet_reader/__init__.py
earlinet_reader/create_html.py
earlinet_reader/dataset.py
earlinet_reader/hirelpp_files.py
earlinet_reader/optical_files.py
earlinet_reader/preprocessor_files.py
earlinet_reader/scripts/__init__.py
earlinet_reader/scripts/plot_dataset.py
earlinet_reader/scripts/plot_elpp.py
earlinet_reader/scripts/plot_optical.py
earlinet_reader/templates/normalize.css
earlinet_reader/templates/single_elpp_file.html
earlinet_reader/templates/single_optical_file.html
earlinet_reader/templates/skeleton.css
earlinet_reader-0.4.0.dist-info/LICENCE.txt
earlinet_reader-0.4.0.dist-info/METADATA
earlinet_reader-0.4.0.dist-info/entry_points.txt
earlinet_reader-0.4.0.dist-info/top_level.txt
earlinet_reader-0.4.2.dist-info/LICENCE.txt
earlinet_reader-0.4.2.dist-info/METADATA
earlinet_reader-0.4.2.dist-info/WHEEL
earlinet_reader-0.4.2.dist-info/entry_points.txt
earlinet_reader-0.4.2.dist-info/top_level.txt
earlinet_reader-0.4.2.dist-info/RECORD
