Metadata-Version: 2.1
Name: earlinet-reader
Version: 0.4.2
Summary: Package to read processed lidar data in the EARLINET NetCDF formats.
Home-page: https://bitbucket.org/iannis_b/earlinet-reader/
Author: Ioannis Binietoglou
Author-email: ioannis@inoe.ro
License: MIT
Keywords: lidar aerosol EARLINET
Platform: UNKNOWN
Classifier: Development Status :: 2 - Pre-Alpha
Classifier: License :: OSI Approved :: MIT License
Classifier: Programming Language :: Python :: 2
Classifier: Intended Audience :: Science/Research
Classifier: Topic :: Scientific/Engineering :: Atmospheric Science
Requires-Dist: numpy
Requires-Dist: matplotlib
Requires-Dist: sphinx
Requires-Dist: jinja2
Requires-Dist: netCDF4
Requires-Dist: anytree
